aocpy/__init__.py
aocpy/cli.py
aocpy/exception.py
aocpy/generate.py
aocpy/puzzle.py
aocpy/utils.py
aocpy/templates/__init__.py
aocpy/templates/cli.py
aocpy/templates/solution.py
aocpy-0.0.1.dist-info/METADATA
aocpy-0.0.1.dist-info/WHEEL
aocpy-0.0.1.dist-info/entry_points.txt
aocpy-0.0.1.dist-info/top_level.txt
aocpy-0.0.1.dist-info/RECORD
