Metadata-Version: 2.1
Name: aocpy
Version: 0.0.1
Summary: Advent of Code Automation
Home-page: https://github.com/SteadBytes/aocpy
Author: Ben Steadman
Author-email: steadmanben1@gmail.com
License: MIT
Platform: UNKNOWN
Classifier: License :: OSI Approved :: MIT License
Classifier: Programming Language :: Python
Classifier: Programming Language :: Python :: 3
Classifier: Programming Language :: Python :: 3.6
Classifier: Programming Language :: Python :: Implementation :: CPython
Classifier: Programming Language :: Python :: Implementation :: PyPy
Requires-Python: >=3.6.0
Requires-Dist: requests
Requires-Dist: beautifulsoup4
Requires-Dist: click
Requires-Dist: pytz
